robota_common_errors/__init__.py
robota_common_errors/analysis.py
robota_common_errors/common_error_collection.py
robota_common_errors/common_error_functions.py
robota_common_errors/common_errors.py
robota_common_errors/report.py
robota_common_errors/output_templates/__init__.py
robota_common_errors/output_templates/build_webpages.py
robota_common_errors-1.1.1.dist-info/LICENSE
robota_common_errors-1.1.1.dist-info/METADATA
robota_common_errors-1.1.1.dist-info/WHEEL
robota_common_errors-1.1.1.dist-info/top_level.txt
robota_common_errors-1.1.1.dist-info/RECORD
