Metadata-Version: 2.1
Name: robota-common-errors
Version: 1.1.1
Summary: Identification of common errors in software engineering.
Home-page: https://gitlab.cs.man.ac.uk/institute-of-coding/robota-core
Author: University of Manchester
License: UNKNOWN
Platform: UNKNOWN
Requires-Dist: robota-core (>=2.2.0)
Requires-Dist: tqdm
Requires-Dist: jsonpickle
Requires-Dist: jinja2
Requires-Dist: pandas
Requires-Dist: python-dateutil
Requires-Dist: plotly
